[
  {
    "id": "eeb5e6918952",
    "title": "中国具有全球影响力的民族法引起日本和欧洲的强烈反对",
    "summary": "",
    "url": "https://asia.nikkei.com/politics/china-s-ethnic-law-with-global-reach-draws-backlash-from-japan-to-europe",
    "source_name": "Nikkei Asia",
    "source_url": "https://asia.nikkei.com",
    "published": "2026-07-02T07:37:05.169374+00:00",
    "categories": [
      "World"
    ],
    "img_url": "",
    "language": "en"
  },
  {
    "id": "e4a2ae2a4eab",
    "title": "巴基斯坦批准1,600公里国家石油管道的最终连接",
    "summary": "",
    "url": "https://asia.nikkei.com/business/energy/pakistan-approves-final-link-in-1-600-km-national-oil-pipeline",
    "source_name": "Nikkei Asia",
    "source_url": "https://asia.nikkei.com",
    "published": "2026-07-02T07:37:05.169361+00:00",
    "categories": [
      "World"
    ],
    "img_url": "",
    "language": "en"
  },
  {
    "id": "83352e5934ac",
    "title": "丰田将车辆规格与人工智能相协调，帮助加快生产",
    "summary": "",
    "url": "https://asia.nikkei.com/business/automobiles/toyota-to-harmonize-vehicle-specs-with-ai-helping-to-speed-production",
    "source_name": "Nikkei Asia",
    "source_url": "https://asia.nikkei.com",
    "published": "2026-07-02T07:37:05.169348+00:00",
    "categories": [
      "Technology"
    ],
    "img_url": "",
    "language": "en"
  },
  {
    "id": "f25ea2a4e4a9",
    "title": "芯片需求带动韩国 6 月出口首次突破 1000 亿美元",
    "summary": "",
    "url": "https://asia.nikkei.com/economy/south-korean-exports-in-june-soar-past-100bn-for-first-time-on-chip-demand",
    "source_name": "Nikkei Asia",
    "source_url": "https://asia.nikkei.com",
    "published": "2026-07-02T07:37:05.169336+00:00",
    "categories": [
      "Economy",
      "World"
    ],
    "img_url": "",
    "language": "en"
  },
  {
    "id": "84755b1f235b",
    "title": "人工智能重塑增长，印度 IT 公司加大收购力度",
    "summary": "",
    "url": "https://asia.nikkei.com/business/technology/indian-it-firms-ramp-up-acquisitions-as-ai-reshapes-growth",
    "source_name": "Nikkei Asia",
    "source_url": "https://asia.nikkei.com",
    "published": "2026-07-02T07:37:05.169323+00:00",
    "categories": [
      "Economy",
      "World"
    ],
    "img_url": "",
    "language": "en"
  },
  {
    "id": "f734d5a93b60",
    "title": "日本将签证费提高五倍以解决过度旅游问题",
    "summary": "",
    "url": "https://asia.nikkei.com/business/travel-leisure/japan-raises-visa-fees-fivefold-to-tackle-overtourism2",
    "source_name": "Nikkei Asia",
    "source_url": "https://asia.nikkei.com",
    "published": "2026-07-02T07:37:05.169311+00:00",
    "categories": [
      "World"
    ],
    "img_url": "",
    "language": "en"
  },
  {
    "id": "b8e0c2ff6267",
    "title": "丑闻发生后澳大利亚着眼于四大会计改革",
    "summary": "",
    "url": "https://asia.nikkei.com/business/companies/australia-eyes-big-four-accounting-reforms-after-scandals",
    "source_name": "Nikkei Asia",
    "source_url": "https://asia.nikkei.com",
    "published": "2026-07-02T07:37:05.169299+00:00",
    "categories": [
      "Politics"
    ],
    "img_url": "",
    "language": "en"
  },
  {
    "id": "6cb0671a00c2",
    "title": "由于进口激增，印度尼西亚六年来首次出现贸易逆差",
    "summary": "",
    "url": "https://asia.nikkei.com/economy/trade/indonesia-logs-first-trade-deficit-in-six-years-as-imports-soar",
    "source_name": "Nikkei Asia",
    "source_url": "https://asia.nikkei.com",
    "published": "2026-07-02T07:37:05.169288+00:00",
    "categories": [
      "Economy",
      "World"
    ],
    "img_url": "",
    "language": "en"
  },
  {
    "id": "59e38bb7f8c6",
    "title": "新加坡在 Nvidia 芯片走私案中查获 4200 万美元",
    "summary": "",
    "url": "https://asia.nikkei.com/spotlight/society/crime/singapore-seizes-42m-home-in-nvidia-chip-smuggling-case",
    "source_name": "Nikkei Asia",
    "source_url": "https://asia.nikkei.com",
    "published": "2026-07-02T07:37:05.169276+00:00",
    "categories": [
      "Economy",
      "Technology"
    ],
    "img_url": "",
    "language": "en"
  },
  {
    "id": "d54d2334562e",
    "title": "电动汽车补贴调整导致比亚迪上半年销量下降16%",
    "summary": "",
    "url": "https://asia.nikkei.com/business/automobiles/byd-s-first-half-sales-fall-16-on-china-s-ev-subsidy-changes",
    "source_name": "Nikkei Asia",
    "source_url": "https://asia.nikkei.com",
    "published": "2026-07-02T07:37:05.169264+00:00",
    "categories": [
      "Economy",
      "Technology"
    ],
    "img_url": "",
    "language": "en"
  },
  {
    "id": "349ce1c75a08",
    "title": "韩国接受 24 小时韩元交易，打破货币“创伤”",
    "summary": "",
    "url": "https://asia.nikkei.com/business/markets/currencies/south-korea-embraces-24-hour-won-trading-in-break-with-currency-trauma",
    "source_name": "Nikkei Asia",
    "source_url": "https://asia.nikkei.com",
    "published": "2026-07-02T07:37:05.169252+00:00",
    "categories": [
      "World"
    ],
    "img_url": "",
    "language": "en"
  },
  {
    "id": "d69fd23b6954",
    "title": "日本、英国、意大利考虑加拿大作为战斗机计划观察员",
    "summary": "",
    "url": "https://asia.nikkei.com/business/aerospace-defense-industries/japan-uk-italy-to-consider-canada-as-observer-in-fighter-jet-program",
    "source_name": "Nikkei Asia",
    "source_url": "https://asia.nikkei.com",
    "published": "2026-07-02T07:37:05.169240+00:00",
    "categories": [
      "World"
    ],
    "img_url": "",
    "language": "en"
  },
  {
    "id": "d96b4b4fea79",
    "title": "川崎重工将通过新股和债券筹集超过 10 亿美元用于人工智能投资",
    "summary": "",
    "url": "https://asia.nikkei.com/business/technology/artificial-intelligence/kawasaki-heavy-to-raise-over-1bn-via-new-shares-bonds-for-ai-investment",
    "source_name": "Nikkei Asia",
    "source_url": "https://asia.nikkei.com",
    "published": "2026-07-02T07:37:05.169227+00:00",
    "categories": [
      "Technology"
    ],
    "img_url": "",
    "language": "en"
  },
  {
    "id": "d042e480a19e",
    "title": "日本将为 Reliance 的印度太阳能和电池项目提供贷款贸易保险",
    "summary": "",
    "url": "https://asia.nikkei.com/economy/trade/japan-to-offer-trade-insurance-on-loan-for-reliance-s-india-solar-battery-effort",
    "source_name": "Nikkei Asia",
    "source_url": "https://asia.nikkei.com",
    "published": "2026-07-02T07:37:05.169215+00:00",
    "categories": [
      "World"
    ],
    "img_url": "",
    "language": "en"
  },
  {
    "id": "8675db9ddc27",
    "title": "随着供应链作用的增强，日本国有银行 JBIC 在美国的融资猛增",
    "summary": "",
    "url": "https://asia.nikkei.com/business/finance/japan-state-lender-jbic-s-us-financing-soars-as-supply-chain-role-grows",
    "source_name": "Nikkei Asia",
    "source_url": "https://asia.nikkei.com",
    "published": "2026-07-02T07:37:05.169202+00:00",
    "categories": [
      "World"
    ],
    "img_url": "",
    "language": "en"
  },
  {
    "id": "a74e9f51a565",
    "title": "日本 SMBC 等公司将为印度电网开发提供高达 4.9 亿美元的贷款",
    "summary": "",
    "url": "https://asia.nikkei.com/business/energy/japan-s-smbc-others-to-loan-up-to-490m-for-india-power-grid-development",
    "source_name": "Nikkei Asia",
    "source_url": "https://asia.nikkei.com",
    "published": "2026-07-02T07:37:05.169190+00:00",
    "categories": [
      "World"
    ],
    "img_url": "",
    "language": "en"
  },
  {
    "id": "02f990b16c8e",
    "title": "Aflac Japan 报告 438 万客户遭到泄露，其中包括银行详细信息",
    "summary": "",
    "url": "https://asia.nikkei.com/spotlight/cybersecurity/aflac-japan-reports-breach-on-4.38m-customers-includes-bank-details",
    "source_name": "Nikkei Asia",
    "source_url": "https://asia.nikkei.com",
    "published": "2026-07-02T07:37:05.169178+00:00",
    "categories": [
      "World"
    ],
    "img_url": "",
    "language": "en"
  },
  {
    "id": "60c7f009adcd",
    "title": "日本 USB 驱动器病毒与先前的阴谋相呼应，与中国军方有联系",
    "summary": "",
    "url": "https://asia.nikkei.com/spotlight/cybersecurity/japan-usb-drive-viruses-echo-earlier-plot-with-links-to-chinese-military",
    "source_name": "Nikkei Asia",
    "source_url": "https://asia.nikkei.com",
    "published": "2026-07-02T07:37:05.169166+00:00",
    "categories": [
      "World"
    ],
    "img_url": "",
    "language": "en"
  },
  {
    "id": "4af7deaddf28",
    "title": "分析：中国的拘留给日本在大连的遗产蒙上了阴影",
    "summary": "",
    "url": "https://asia.nikkei.com/editor-s-picks/china-up-close/analysis-china-detentions-cast-shadow-over-japan-s-legacy-in-dalian",
    "source_name": "Nikkei Asia",
    "source_url": "https://asia.nikkei.com",
    "published": "2026-07-02T07:37:05.169153+00:00",
    "categories": [
      "World"
    ],
    "img_url": "",
    "language": "en"
  },
  {
    "id": "8333acb7df7d",
    "title": "中国太阳能电池板材料合资公司成立数月后仍处于休眠状态",
    "summary": "",
    "url": "https://asia.nikkei.com/business/energy/china-solar-panel-material-jv-remains-dormant-months-after-launch",
    "source_name": "Nikkei Asia",
    "source_url": "https://asia.nikkei.com",
    "published": "2026-07-02T07:37:05.169139+00:00",
    "categories": [
      "World"
    ],
    "img_url": "",
    "language": "en"
  },
  {
    "id": "45e1471fb6e6",
    "title": "中国的影响力管道已经活跃在日本的信息领域",
    "summary": "",
    "url": "https://asia.nikkei.com/opinion/china-s-influence-pipeline-is-already-active-in-japan-s-information-space",
    "source_name": "Nikkei Asia",
    "source_url": "https://asia.nikkei.com",
    "published": "2026-07-02T07:37:05.169127+00:00",
    "categories": [
      "World"
    ],
    "img_url": "",
    "language": "en"
  },
  {
    "id": "9d0de9e45c4e",
    "title": "印尼组织指控金融法修订允许洗钱",
    "summary": "",
    "url": "https://asia.nikkei.com/economy/indonesian-group-alleges-financial-law-revision-allows-money-laundering",
    "source_name": "Nikkei Asia",
    "source_url": "https://asia.nikkei.com",
    "published": "2026-07-02T07:37:05.169113+00:00",
    "categories": [
      "World"
    ],
    "img_url": "",
    "language": "en"
  },
  {
    "id": "24fe40d9cc48",
    "title": "丰田将部分弥补停止电动汽车开发后供应商的损失",
    "summary": "",
    "url": "https://asia.nikkei.com/business/automobiles/toyota-to-partly-cover-supplier-losses-after-halting-ev-development",
    "source_name": "Nikkei Asia",
    "source_url": "https://asia.nikkei.com",
    "published": "2026-07-02T07:37:05.169096+00:00",
    "categories": [
      "World"
    ],
    "img_url": "",
    "language": "en"
  },
  {
    "id": "2f3daa75d846",
    "title": "苹果将​​推出 5 款新 iPhone 机型，以在内存短缺的情况下赢得市场份额",
    "summary": "",
    "url": "https://asia.nikkei.com/business/technology/apple-to-launch-5-new-iphone-models-to-gain-market-share-amid-memory-crunch",
    "source_name": "Nikkei Asia",
    "source_url": "https://asia.nikkei.com",
    "published": "2026-07-02T07:37:05.169078+00:00",
    "categories": [
      "Technology"
    ],
    "img_url": "",
    "language": "en"
  },
  {
    "id": "cae1bdb53bd0",
    "title": "武田 (Takeda) 与 Insilico 达成价值高达 6 亿美元的人工智能主导药物发现交易",
    "summary": "",
    "url": "https://asia.nikkei.com/business/pharmaceuticals/takeda-and-insilico-strike-ai-led-drug-discovery-deal-worth-up-to-600m",
    "source_name": "Nikkei Asia",
    "source_url": "https://asia.nikkei.com",
    "published": "2026-07-02T07:37:05.169064+00:00",
    "categories": [
      "Technology",
      "Science"
    ],
    "img_url": "",
    "language": "en"
  },
  {
    "id": "607dc743113a",
    "title": "书籍：日本是海上强国吗？",
    "summary": "",
    "url": "https://asia.nikkei.com/life-arts/books/books-is-japan-a-maritime-great-power",
    "source_name": "Nikkei Asia",
    "source_url": "https://asia.nikkei.com",
    "published": "2026-07-02T07:37:05.169049+00:00",
    "categories": [
      "World"
    ],
    "img_url": "",
    "language": "en"
  },
  {
    "id": "3e1bafafa42f",
    "title": "欧盟和中国是否会爆发贸易战？ 5 件事要知道",
    "summary": "",
    "url": "https://asia.nikkei.com/economy/trade/are-the-eu-and-china-heading-for-a-trade-war-5-things-to-know",
    "source_name": "Nikkei Asia",
    "source_url": "https://asia.nikkei.com",
    "published": "2026-07-02T07:37:05.169035+00:00",
    "categories": [
      "World"
    ],
    "img_url": "",
    "language": "en"
  },
  {
    "id": "beac03c79a44",
    "title": "香港李家超在自己的关键一年加强了对习近平的拥抱",
    "summary": "",
    "url": "https://asia.nikkei.com/politics/hong-kong-s-john-lee-tightens-embrace-of-xi-in-pivotal-year-for-himself",
    "source_name": "Nikkei Asia",
    "source_url": "https://asia.nikkei.com",
    "published": "2026-07-02T07:37:05.169019+00:00",
    "categories": [
      "Politics"
    ],
    "img_url": "",
    "language": "en"
  },
  {
    "id": "8afc840c4dea",
    "title": "补贴退坡影响汽车、家电销售，中国面临政策考验",
    "summary": "",
    "url": "https://asia.nikkei.com/economy/china-faces-policy-test-as-subsidy-pullback-hits-auto-appliance-sales",
    "source_name": "Nikkei Asia",
    "source_url": "https://asia.nikkei.com",
    "published": "2026-07-02T07:37:05.169003+00:00",
    "categories": [
      "World"
    ],
    "img_url": "",
    "language": "en"
  },
  {
    "id": "5defb7f4698d",
    "title": "日本电通将子公司私有化",
    "summary": "",
    "url": "https://asia.nikkei.com/business/business-deals/japan-s-dentsu-to-take-subsidiary-private",
    "source_name": "Nikkei Asia",
    "source_url": "https://asia.nikkei.com",
    "published": "2026-07-02T07:37:05.168975+00:00",
    "categories": [
      "World"
    ],
    "img_url": "",
    "language": "en"
  }
]